exoral/__init__.py
exoral/admin.py
exoral/apps.py
exoral/models.py
exoral/tests.py
exoral/urls.py
exoral/views.py
exoral/migrations/0001_initial.py
exoral/migrations/0002_frage__alter_abgestimmte_benutzer.py
exoral/migrations/__init__.py
exoral/static/exoral/select2/css/select2.css
exoral/static/exoral/select2/css/select2.min.css
exoral/static/exoral/select2/js/select2.full.js
exoral/static/exoral/select2/js/select2.full.min.js
exoral/static/exoral/select2/js/select2.js
exoral/static/exoral/select2/js/select2.min.js
exoral/static/exoral/select2/js/i18n/af.js
exoral/static/exoral/select2/js/i18n/ar.js
exoral/static/exoral/select2/js/i18n/az.js
exoral/static/exoral/select2/js/i18n/bg.js
exoral/static/exoral/select2/js/i18n/bn.js
exoral/static/exoral/select2/js/i18n/bs.js
exoral/static/exoral/select2/js/i18n/ca.js
exoral/static/exoral/select2/js/i18n/cs.js
exoral/static/exoral/select2/js/i18n/da.js
exoral/static/exoral/select2/js/i18n/de.js
exoral/static/exoral/select2/js/i18n/dsb.js
exoral/static/exoral/select2/js/i18n/el.js
exoral/static/exoral/select2/js/i18n/en.js
exoral/static/exoral/select2/js/i18n/es.js
exoral/static/exoral/select2/js/i18n/et.js
exoral/static/exoral/select2/js/i18n/eu.js
exoral/static/exoral/select2/js/i18n/fa.js
exoral/static/exoral/select2/js/i18n/fi.js
exoral/static/exoral/select2/js/i18n/fr.js
exoral/static/exoral/select2/js/i18n/gl.js
exoral/static/exoral/select2/js/i18n/he.js
exoral/static/exoral/select2/js/i18n/hi.js
exoral/static/exoral/select2/js/i18n/hr.js
exoral/static/exoral/select2/js/i18n/hsb.js
exoral/static/exoral/select2/js/i18n/hu.js
exoral/static/exoral/select2/js/i18n/hy.js
exoral/static/exoral/select2/js/i18n/id.js
exoral/static/exoral/select2/js/i18n/is.js
exoral/static/exoral/select2/js/i18n/it.js
exoral/static/exoral/select2/js/i18n/ja.js
exoral/static/exoral/select2/js/i18n/ka.js
exoral/static/exoral/select2/js/i18n/km.js
exoral/static/exoral/select2/js/i18n/ko.js
exoral/static/exoral/select2/js/i18n/lt.js
django_exoral-0.2.2.dist-info/LICENSE
django_exoral-0.2.2.dist-info/METADATA
django_exoral-0.2.2.dist-info/WHEEL
django_exoral-0.2.2.dist-info/top_level.txt
django_exoral-0.2.2.dist-info/RECORD
